semantiva_optimize/__init__.py
semantiva_optimize/constraints.py
semantiva_optimize/factory.py
semantiva_optimize/termination.py
semantiva_optimize-0.1.0.dist-info/licenses/LICENSE
semantiva_optimize-0.1.0.dist-info/METADATA
semantiva_optimize-0.1.0.dist-info/WHEEL
semantiva_optimize-0.1.0.dist-info/entry_points.txt
semantiva_optimize-0.1.0.dist-info/top_level.txt
semantiva_optimize-0.1.0.dist-info/RECORD
