Metadata-Version: 2.4
Name: semantiva-optimize
Version: 0.1.0
Summary: Optimization extension for Semantiva: Local Convex strategy and generic optimizer processor.
License: Apache-2.0
Requires-Python: >=3.10.12
License-File: LICENSE
Requires-Dist: numpy>=2.2.1
Requires-Dist: scipy
Requires-Dist: semantiva>=0.5.0rc2
Dynamic: license-file
